labdaemon/__init__.py
labdaemon/_version.py
labdaemon/context.py
labdaemon/daemon.py
labdaemon/exceptions.py
labdaemon/handlers.py
labdaemon/utils.py
labdaemon/patterns/__init__.py
labdaemon/patterns/gui.py
labdaemon/patterns/launcher.py
labdaemon/patterns/setup.py
labdaemon/server/__init__.py
labdaemon/server/client.py
labdaemon/server/errors.py
labdaemon/server/managers.py
labdaemon/server/server.py
labdaemon/tests/__init__.py
labdaemon/tests/test_daemon.py
labdaemon/tests/test_patterns.py
labdaemon/tests/test_server.py
labdaemon-1.0.0.dist-info/METADATA
labdaemon-1.0.0.dist-info/WHEEL
labdaemon-1.0.0.dist-info/entry_points.txt
labdaemon-1.0.0.dist-info/licenses/LICENSE
labdaemon-1.0.0.dist-info/RECORD
