Metadata-Version: 2.4
Name: labdaemon
Version: 1.0.0
Summary: A Python framework for instrument control and experiment automation.
Project-URL: Homepage, https://docs.samsci.com/labdaemon/
Project-URL: Documentation, https://docs.samsci.com/labdaemon/
Project-URL: Repository, https://github.com/qnslab/labdaemon
Project-URL: Issues, https://github.com/qnslab/labdaemon/issues
Author: The LabDaemon Team
License: AGPL-3.0-or-later
License-File: LICENSE
Keywords: automation,control,experiment,instrument,laboratory
Classifier: Development Status :: 5 - Production/Stable
Classifier: Intended Audience :: Science/Research
Classifier: License :: OSI Approved :: MIT License
Classifier: Programming Language :: Python :: 3
Classifier: Programming Language :: Python :: 3.8
Classifier: Programming Language :: Python :: 3.9
Classifier: Programming Language :: Python :: 3.10
Classifier: Programming Language :: Python :: 3.11
Classifier: Programming Language :: Python :: 3.12
Requires-Python: >=3.8
Provides-Extra: dev
Requires-Dist: fastapi; extra == 'dev'
Requires-Dist: httpx; extra == 'dev'
Requires-Dist: numpy; extra == 'dev'
Requires-Dist: pytest; extra == 'dev'
Requires-Dist: requests>=2.25.0; extra == 'dev'
Requires-Dist: sse-starlette; extra == 'dev'
Requires-Dist: uvicorn; extra == 'dev'
Provides-Extra: launcher
Requires-Dist: psutil; extra == 'launcher'
Requires-Dist: pyqt5>=5.15.0; extra == 'launcher'
Requires-Dist: requests>=2.25.0; extra == 'launcher'
Provides-Extra: server
Requires-Dist: fastapi; extra == 'server'
Requires-Dist: numpy; extra == 'server'
Requires-Dist: requests>=2.25.0; extra == 'server'
Requires-Dist: sse-starlette; extra == 'server'
Requires-Dist: uvicorn; extra == 'server'
